Metadata-Version: 1.0
Name: telescope-ng
Version: 0.1
Summary: RDF data mapper and SPARQL query builder (fork)
Home-page: http://bitbucket.org/ww/telescope
Author: Brian Beck
Author-email: UNKNOWN
License: MIT
Keywords: rdf rdflib sparql orm
Platform: UNKNOWN
